vtc/__init__.py
vtc/_consts.py
vtc/_framerate.py
vtc/_premiere_ticks.py
vtc/_range.py
vtc/_timecode.py
vtc/_timecode_dropframe.py
vtc/_timecode_parsers.py
vtc/_timecode_sections.py
vtc/_version.py
vtc-0.1.0.dist-info/LICENSE
vtc-0.1.0.dist-info/METADATA
vtc-0.1.0.dist-info/WHEEL
vtc-0.1.0.dist-info/top_level.txt
vtc-0.1.0.dist-info/RECORD
